TOPSIS/__init__.py
TOPSIS/__main__.py
TOPSIS_KARAN_101903072-0.0.0.dist-info/LICENSE
TOPSIS_KARAN_101903072-0.0.0.dist-info/METADATA
TOPSIS_KARAN_101903072-0.0.0.dist-info/WHEEL
TOPSIS_KARAN_101903072-0.0.0.dist-info/entry_points.txt
TOPSIS_KARAN_101903072-0.0.0.dist-info/top_level.txt
TOPSIS_KARAN_101903072-0.0.0.dist-info/RECORD
